[
  {
    "id": "ThomasCup-Perancis-Thailand",
    "sport": "badminton",
    "league": "Piala Thomas Tim - Tim Pria",
    "league_logo": "https://static.flashscore.com/res/image/data/UJi4Yz8j-23xncWPM.png",
    "team1": { "name": "Perancis" },
    "team2": { "name": "Thailand" },
    "kickoff_date": "2026-04-24",
    "kickoff_time": "17:00",
    "duration": 180,
    "channels": [
      { "name": "COURT 1 SD", "url": "https://plasak.pages.dev/?id=court1" },
      { "name": "COURT 1 HD", "url": "https://plasak.pages.dev/?id=court11" },
      { "name": "COURT 1 AUTO", "url": "https://plasak.pages.dev/?id=court111" }
  ]
  },
  {
    "id": "UberCup-India-Denmark",
    "sport": "badminton",
    "league": "Piala Uber Tim - Tim Wanita",
    "league_logo": "https://static.flashscore.com/res/image/data/UJi4Yz8j-23xncWPM.png",
    "team1": { "name": "India (Women)" },
    "team2": { "name": "Denmark (Women)" },
    "kickoff_date": "2026-04-24",
    "kickoff_time": "17:00",
    "duration": 180,
    "channels": [
      { "name": "COURT 2 SD", "url": "https://plasak.pages.dev/?id=court1" },
      { "name": "COURT 2 HD", "url": "https://plasak.pages.dev/?id=court22" },
      { "name": "COURT 2 AUTO", "url": "https://plasak.pages.dev/?id=court22" }
    ]
  },
  {
    "id": "UberCup-Korsel-Spanyol",
    "sport": "badminton",
    "league": "Piala Uber Tim - Tim Wanita",
    "league_logo": "https://static.flashscore.com/res/image/data/UJi4Yz8j-23xncWPM.png",
    "team1": { "name": "Korea Selatan (Women)" },
    "team2": { "name": "Spanyol (Women)" },
    "kickoff_date": "2026-04-24",
    "kickoff_time": "17:00",
    "duration": 180,
    "channels": [
      { "name": "Court 1", "url": "https://plasak.pages.dev/?id=badminton-8" }
    ]
  },
  {
    "id": "ThomasCup-Denmark-Korsel",
    "sport": "badminton",
    "league": "Piala Thomas Tim - Tim Pria",
    "league_logo": "https://static.flashscore.com/res/image/data/UJi4Yz8j-23xncWPM.png",
    "team1": { "name": "Denmark" },
    "team2": { "name": "Korea Selatan" },
    "kickoff_date": "2026-04-24",
    "kickoff_time": "23:30",
    "duration": 180,
    "channels": [
      { "name": "COURT 3 SD", "url": "https://plasak.pages.dev/?id=court3" },
      { "name": "COURT 3 HD", "url": "https://plasak.pages.dev/?id=court33" },
      { "name": "COURT 3 AUTO", "url": "https://plasak.pages.dev/?id=court33" }
    ]
  },
  {
    "id": "ThomasCup-Indonesia-Aljazair",
    "sport": "badminton",
    "league": "Piala Thomas Tim - Tim Pria",
    "league_logo": "https://static.flashscore.com/res/image/data/UJi4Yz8j-23xncWPM.png",
    "team1": { "name": "Indonesia" },
    "team2": { "name": "Aljazair" },
    "kickoff_date": "2026-04-24",
    "kickoff_time": "23:30",
    "duration": 180,
    "channels": [
      { "name": "Court 1", "url": "https://plasak.pages.dev/?id=badminton-5" }
    ]
  },
  {
    "id": "UberCup-Thailand-Bulgaria",
    "sport": "badminton",
    "league": "Piala Uber Tim - Tim Wanita",
    "league_logo": "https://static.flashscore.com/res/image/data/UJi4Yz8j-23xncWPM.png",
    "team1": { "name": "Thailand (Women)" },
    "team2": { "name": "Bulgaria (Women)" },
    "kickoff_date": "2026-04-24",
    "kickoff_time": "23:30",
    "duration": 180,
    "channels": [
      { "name": "Court 1", "url": "https://plasak.pages.dev/?id=badminton-9" }
    ]
  }
]